nonebot_plugin_grouplock/__init__.py
nonebot_plugin_grouplock/models/__init__.py
nonebot_plugin_grouplock/models/group.py
nonebot_plugin_grouplock/utils/__init__.py
nonebot_plugin_grouplock/utils/handel.py
nonebot_plugin_grouplock/utils/path.py
nonebot_plugin_grouplock-0.0.3.dist-info/LICENSE
nonebot_plugin_grouplock-0.0.3.dist-info/WHEEL
nonebot_plugin_grouplock-0.0.3.dist-info/METADATA
nonebot_plugin_grouplock-0.0.3.dist-info/RECORD
