Metadata-Version: 2.1
Name: nonebot-plugin-grouplock
Version: 0.0.3
Summary: 一个基于nonebot2和go-cqhttp的群聊人数锁定插件
Home-page: https://github.com/ZM25XC/nonebot-plugin-grouplock
License: MIT
Author: ZM25XC
Author-email: xingling25@qq.com
Requires-Python: >=3.8,<4.0
Classifier: License :: OSI Approved :: MIT License
Classifier: Programming Language :: Python :: 3
Classifier: Programming Language :: Python :: 3.8
Classifier: Programming Language :: Python :: 3.9
Classifier: Programming Language :: Python :: 3.10
Requires-Dist: nonebot-adapter-onebot (>=2.2.3,<3.0.0)
Requires-Dist: nonebot2 (>=2.0.0,<3.0.0)
Requires-Dist: tortoise-orm (>=0.19.3,<0.20.0)
